ExperimentsLogReader/__init__.py
ExperimentsLogReader/__name__.py
ExperimentsLogReader/experimentsLogReader.py
ExperimentsLogReader/scan.py
ExperimentsLogReader/parsers/__init__.py
ExperimentsLogReader/parsers/_configparser.py
ExperimentsLogReader/parsers/testConfigParser.py
experimentsLogReader-2.1.1.dist-info/METADATA
experimentsLogReader-2.1.1.dist-info/WHEEL
experimentsLogReader-2.1.1.dist-info/top_level.txt
experimentsLogReader-2.1.1.dist-info/RECORD
