Metadata-Version: 2.1
Name: experimentsLogReader
Version: 2.1.1
Summary: Log file reader for Radio Astronomy
Home-page: https://github.com/sklandrausis/ExperimentsLogReader
Author: Jānis Šteinbergs
Author-email: janis.akmenskalns@gmail.com
License: UNKNOWN
Keywords: VIRAC
Platform: UNKNOWN
Classifier: Programming Language :: Python :: 3
Classifier: License :: OSI Approved :: MIT License
Classifier: Operating System :: OS Independent
